paptools/__init__.py
paptools/debugging.py
paptools/settings.py
paptools/constants/__init__.py
paptools/constants/math.py
paptools/constants/physics.py
paptools/core/__init__.py
paptools/core/array.py
paptools/core/number.py
paptools/math/__init__.py
paptools/math/functions.py
paptools/math/wrap.py
paptools/statistics/__init__.py
paptools/statistics/tests.py
paptools/utils/__init__.py
paptools/validators/__init__.py
paptools/validators/input.py
paptools-0.1.6.dist-info/licenses/LICENSE
paptools-0.1.6.dist-info/METADATA
paptools-0.1.6.dist-info/WHEEL
paptools-0.1.6.dist-info/top_level.txt
paptools-0.1.6.dist-info/RECORD
