Metadata-Version: 2.4
Name: paptools
Version: 0.1.6
Summary: A python wrapper combining functionality of numpy, sympy, unyt, and matplotlib, featuring automatic symbolic and numeric error propagation, unit handling and conversion, statistical functionality and more.Tools for plotting, fitting and data handling
Author-email: Jonas Mueller <jonas.mueller.wpk@proton.me>
License: MIT License
Project-URL: Homepage, https://github.com/jmueller209/paptools.git
Keywords: uncertainty,sympy,units,error,propagation,paptools
Requires-Python: >=3.9
License-File: LICENSE
Requires-Dist: numpy
Requires-Dist: scipy
Requires-Dist: sympy
Requires-Dist: unyt
Dynamic: license-file
